appstoreconnect_BPHvZ/__init__.py
appstoreconnect_BPHvZ/__version__.py
appstoreconnect_BPHvZ/api.py
appstoreconnect_BPHvZ/resources.py
appstoreconnect_BPHvZ-0.10.1.dist-info/LICENSE
appstoreconnect_BPHvZ-0.10.1.dist-info/METADATA
appstoreconnect_BPHvZ-0.10.1.dist-info/WHEEL
appstoreconnect_BPHvZ-0.10.1.dist-info/top_level.txt
appstoreconnect_BPHvZ-0.10.1.dist-info/RECORD
