Metadata-Version: 2.1
Name: appstoreconnect-BPHvZ
Version: 0.10.1
Summary: A Python wrapper around Apple App Store Api
Home-page: https://github.com/BPHvZ/appstoreconnectapi
Author: BPHvZ
Author-email: simpleappsfarm@gmail.com
License: MIT
Classifier: License :: OSI Approved :: MIT License
Classifier: Programming Language :: Python
Classifier: Programming Language :: Python :: 3
Classifier: Programming Language :: Python :: 3.6
Classifier: Programming Language :: Python :: 3.7
Classifier: Programming Language :: Python :: 3.8
Classifier: Programming Language :: Python :: 3.9
Requires-Python: >=3.6.0
License-File: LICENSE
Requires-Dist: requests (==2.*,>=2.20.1)
Requires-Dist: PyJWT (==2.*,>=2.4.0)
